{
  "first_name": "Olive",
  "last_name": "Kopp",
  "gender": "F",
  "grade": "6th grade",
  "school": "Saint Michael CYOKS",
  "school_code": "SMA1",
  "results": {
    "4/26/2025": {
      "results": [
        {
          "id": "209",
          "event": "100",
          "overall_place": 19,
          "heat": 3,
          "place": 8,
          "result": "17.36",
          "meetName": "CYO #3 2025 Afternoon Track",
          "meetDate": "4/26/2025"
        },
        {
          "id": "225",
          "event": "60",
          "overall_place": null,
          "heat": 3,
          "place": null,
          "result": "DNS",
          "meetName": "CYO #3 2025 Afternoon Track",
          "meetDate": "4/26/2025"
        },
        {
          "id": "96",
          "event": "LJ",
          "overall_place": 19,
          "heat": 3,
          "place": 9,
          "result": "9-07.50",
          "meetName": "CYO #3 2025 Afternoon Field",
          "meetDate": "4/26/2025"
        },
        {
          "id": "102",
          "event": "SP",
          "overall_place": 10,
          "heat": 1,
          "place": 10,
          "result": "15-02.00",
          "meetName": "CYO #3 2025 Afternoon Field",
          "meetDate": "4/26/2025"
        }
      ]
    }
  }
}